sesg/__init__.py
sesg/evaluation/__init__.py
sesg/evaluation/evaluation_factory.py
sesg/evaluation/graph.py
sesg/py.typed
sesg/scopus/__init__.py
sesg/scopus/client.py
sesg/scopus/mutable_cycle.py
sesg/search_string/__init__.py
sesg/search_string/formulation.py
sesg/search_string/generation.py
sesg/similar_words/__init__.py
sesg/similar_words/bert_strategy.py
sesg/similar_words/protocol.py
sesg/similar_words/stemming_filter.py
sesg/snowballing/__init__.py
sesg/snowballing/fuzzy_bsb.py
sesg/topic_extraction/__init__.py
sesg/topic_extraction/bertopic_strategy.py
sesg/topic_extraction/create_docs.py
sesg/topic_extraction/lda_strategy.py
sesg-0.0.59.dist-info/LICENSE
sesg-0.0.59.dist-info/METADATA
sesg-0.0.59.dist-info/WHEEL
sesg-0.0.59.dist-info/RECORD
