Metadata-Version: 2.1
Name: sesg
Version: 0.0.59
Summary: SeSG is a tool developed to help Systematic Literature Review researchers, specifically at the step of building a search string.
License: GPL-3.0-only
Author: Demetrius Panovitch
Author-email: demetrius.mp789@gmail.com
Requires-Python: >=3.10,<3.11
Classifier: Development Status :: 3 - Alpha
Classifier: Intended Audience :: Science/Research
Classifier: License :: OSI Approved :: GNU General Public License v3 (GPLv3)
Classifier: Natural Language :: English
Classifier: Programming Language :: Python :: 3
Classifier: Programming Language :: Python :: 3.10
Requires-Dist: aiometer (>=0.4.0,<0.5.0)
Requires-Dist: bertopic (>=0.14.1,<0.15.0)
Requires-Dist: graphviz (>=0.20.1,<0.21.0)
Requires-Dist: httpx (>=0.24.0,<0.25.0)
Requires-Dist: nltk (>=3.8.1,<4.0.0)
Requires-Dist: numpy (==1.23.5)
Requires-Dist: rapidfuzz (>=3.0.0,<4.0.0)
Requires-Dist: requests (>=2.31.0,<3.0.0)
Requires-Dist: scikit-learn (>=1.2.2,<2.0.0)
Requires-Dist: tenacity (>=8.2.2,<9.0.0)
Requires-Dist: torch (==2.0.0)
Requires-Dist: transformers (>=4.30.2,<5.0.0)
Requires-Dist: umap-learn (>=0.5.3,<0.6.0)
Project-URL: Documentation, https://sesg.readthedocs.io/en/latest/
Project-URL: Issue Tracker, https://github.com/demetrius-mp/sesg/issues
Project-URL: Source Code, https://github.com/demetrius-mp/sesg
